dawatoma/__init__.py
dawatoma/fp_sequence.py
dawatoma/melody.py
dawatoma/note_dict.py
dawatoma/sequence.py
dawatoma/sgen.py
dawatoma-0.2.1.dist-info/LICENSE.txt
dawatoma-0.2.1.dist-info/METADATA
dawatoma-0.2.1.dist-info/WHEEL
dawatoma-0.2.1.dist-info/top_level.txt
dawatoma-0.2.1.dist-info/RECORD
