Metadata-Version: 2.1
Name: dawatoma
Version: 0.2.1
Summary: DAW Automation - music idea generation software
Home-page: https://www.mrmultimediator.github.io/
Author: MrMultiMediator
Author-email: mrmultimediator@gmail.com
License-File: LICENSE.txt
Requires-Dist: MIDIUtil (>=1.2.1)
Requires-Dist: attrs (>=21.2.0)
